pypgsvg/__init__.py
pypgsvg/__main__.py
pypgsvg/colors.py
pypgsvg/database_service.py
pypgsvg/db_parser.py
pypgsvg/erd_generator.py
pypgsvg/erd_service.py
pypgsvg/layout_optimizer.py
pypgsvg/metadata_injector.py
pypgsvg/server.py
pypgsvg/svg.css
pypgsvg/svg_interactivity.js
pypgsvg/svg_utils.py
pypgsvg/utils.py
pypgsvg-1.2.52.dist-info/licenses/LICENSE
pypgsvg-1.2.52.dist-info/METADATA
pypgsvg-1.2.52.dist-info/WHEEL
pypgsvg-1.2.52.dist-info/entry_points.txt
pypgsvg-1.2.52.dist-info/top_level.txt
pypgsvg-1.2.52.dist-info/RECORD
