Metadata-Version: 2.4
Name: pypgsvg
Version: 1.2.52
Summary: Generate SVG Entity Relationship Diagrams from PostgreSQL database dump files
Home-page: https://github.com/blackburnd/pypgsvg
Author: Daniel Blackburn
Author-email: Daniel Blackburn <blackburnd@gmail.com>
License: MIT License
Project-URL: Homepage, https://github.com/blackburnd/pypgsvg
Project-URL: Bug Reports, https://github.com/blackburnd/pypgsvg/issues
Project-URL: Source Code, https://github.com/blackburnd/pypgsvg
Project-URL: Documentation, https://github.com/blackburnd/pypgsvg#readme
Keywords: postgresql,database,erd,diagram,svg,graphviz,schema,visualization
Classifier: Development Status :: 4 - Beta
Classifier: Intended Audience :: Developers
Classifier: Intended Audience :: System Administrators
Classifier: License :: OSI Approved :: MIT License
Classifier: Operating System :: OS Independent
Classifier: Programming Language :: Python :: 3
Classifier: Programming Language :: Python :: 3.8
Classifier: Programming Language :: Python :: 3.9
Classifier: Programming Language :: Python :: 3.10
Classifier: Programming Language :: Python :: 3.11
Classifier: Programming Language :: Python :: 3.12
Classifier: Programming Language :: Python :: 3.13
Classifier: Topic :: Database
Classifier: Topic :: Documentation
Classifier: Topic :: Software Development :: Documentation
Classifier: Topic :: Utilities
Requires-Python: >=3.8
License-File: LICENSE
Requires-Dist: graphviz>=0.20.0
Provides-Extra: dev
Requires-Dist: pytest>=7.0.0; extra == "dev"
Requires-Dist: pytest-cov>=4.0.0; extra == "dev"
Requires-Dist: black>=22.0.0; extra == "dev"
Requires-Dist: flake8>=4.0.0; extra == "dev"
Requires-Dist: mypy>=1.0.0; extra == "dev"
Provides-Extra: test
Requires-Dist: pytest>=7.0.0; extra == "test"
Requires-Dist: pytest-cov>=4.0.0; extra == "test"
Requires-Dist: pytest-asyncio>=0.23.0; extra == "test"
Requires-Dist: playwright>=1.37.0; extra == "test"
Dynamic: author
Dynamic: home-page
Dynamic: license-file
Dynamic: requires-python
